beamformer/__init__.py
beamformer/beamform.py
beamformer/souden_mvdr.py
beamformer/utils.py
beamformer_gpu-0.1.0.dist-info/LICENSE
beamformer_gpu-0.1.0.dist-info/METADATA
beamformer_gpu-0.1.0.dist-info/WHEEL
beamformer_gpu-0.1.0.dist-info/top_level.txt
beamformer_gpu-0.1.0.dist-info/RECORD
