Metadata-Version: 2.1
Name: beamformer-gpu
Version: 0.1.0
Summary: Souden MVDR beamformer on GPU with CuPy
Home-page: https://github.com/desh2608/beamformer
Author: Desh Raj
Author-email: r.desh26@gmail.com
License: UNKNOWN
Keywords: speech enhancement beamformer
Platform: UNKNOWN
License-File: LICENSE
